serverless_container_constructs/__init__.py
serverless_container_constructs/py.typed
serverless_container_constructs/_jsii/__init__.py
serverless_container_constructs/_jsii/serverless-container-constructs@0.1.21.jsii.tgz
serverless_container_constructs-0.1.21.dist-info/LICENSE
serverless_container_constructs-0.1.21.dist-info/METADATA
serverless_container_constructs-0.1.21.dist-info/WHEEL
serverless_container_constructs-0.1.21.dist-info/top_level.txt
serverless_container_constructs-0.1.21.dist-info/RECORD
