Metadata-Version: 2.1
Name: serverless-container-constructs
Version: 0.1.21
Summary: CDK patterns for modern application with serverless containers on AWS
Home-page: https://github.com/aws-samples/serverless-container-constructs
Author: Pahud Hsieh<hunhsieh@amazon.com>
License: UNLICENSED
Project-URL: Source, https://github.com/aws-samples/serverless-container-constructs
Platform: UNKNOWN
Classifier: Intended Audience :: Developers
Classifier: Operating System :: OS Independent
Classifier: Programming Language :: JavaScript
Classifier: Programming Language :: Python :: 3 :: Only
Classifier: Programming Language :: Python :: 3.6
Classifier: Programming Language :: Python :: 3.7
Classifier: Programming Language :: Python :: 3.8
Classifier: Programming Language :: Python :: 3.9
Classifier: Typing :: Typed
Classifier: Development Status :: 5 - Production/Stable
Requires-Python: >=3.6
License-File: LICENSE
Requires-Dist: aws-cdk-lib (<3.0.0,>=2.11.0)
Requires-Dist: cdk-nag (<3.0.0,>=2.0.0)
Requires-Dist: constructs (<11.0.0,>=10.0.5)
Requires-Dist: jsii (<2.0.0,>=1.55.1)
Requires-Dist: publication (>=0.0.3)
